TimezoneTimeFinder/TimezoneTimeFinder12h.py
TimezoneTimeFinder/TimezoneTimeFinder24h.py
TimezoneTimeFinder/__init__.py
TimezoneTimeFinder-0.0.1.dist-info/LICENCE
TimezoneTimeFinder-0.0.1.dist-info/METADATA
TimezoneTimeFinder-0.0.1.dist-info/WHEEL
TimezoneTimeFinder-0.0.1.dist-info/top_level.txt
TimezoneTimeFinder-0.0.1.dist-info/RECORD
